docker_cicd_manager/__init__.py
docker_cicd_manager/docker_manager.py
docker_cicd_manager/exceptions.py
dockepy-0.1.1.dist-info/METADATA
dockepy-0.1.1.dist-info/WHEEL
dockepy-0.1.1.dist-info/top_level.txt
dockepy-0.1.1.dist-info/RECORD
