Metadata-Version: 2.4
Name: dockepy
Version: 0.1.1
Summary: A Python library for Docker container management and GitHub Actions CI/CD integration
Author-email: Leonardo Hemming <leonardohemming@gmail.com>
License-Expression: MIT
Project-URL: Homepage, https://github.com/ldsh-dev/dockepy
Project-URL: Repository, https://github.com/ldsh-dev/dockepy
Project-URL: Issues, https://github.com/ldsh-dev/dockepy/issues
Classifier: Development Status :: 3 - Alpha
Classifier: Intended Audience :: Developers
Classifier: Operating System :: OS Independent
Classifier: Programming Language :: Python :: 3
Classifier: Programming Language :: Python :: 3.9
Classifier: Programming Language :: Python :: 3.10
Classifier: Programming Language :: Python :: 3.11
Classifier: Programming Language :: Python :: 3.12
Classifier: Programming Language :: Python :: 3.13
Requires-Python: >=3.9
Requires-Dist: docker>=7.1.0
Requires-Dist: PyYAML>=6.0
Requires-Dist: requests>=2.31.0
Provides-Extra: dev
Requires-Dist: pytest>=7.4.0; extra == "dev"
Requires-Dist: pytest-cov>=4.1.0; extra == "dev"
Requires-Dist: black>=23.0.0; extra == "dev"
Requires-Dist: flake8>=6.0.0; extra == "dev"
Requires-Dist: mypy>=1.5.0; extra == "dev"
Requires-Dist: types-docker>=7.1.0; extra == "dev"
Requires-Dist: build>=1.0.0; extra == "dev"
Requires-Dist: twine>=4.0.0; extra == "dev"
Requires-Dist: toml>=0.10.0; extra == "dev"
